open_humans_tornado_oauth2.py
open_humans_tornado_oauth2-2.1.0.dist-info/DESCRIPTION.rst
open_humans_tornado_oauth2-2.1.0.dist-info/METADATA
open_humans_tornado_oauth2-2.1.0.dist-info/RECORD
open_humans_tornado_oauth2-2.1.0.dist-info/WHEEL
open_humans_tornado_oauth2-2.1.0.dist-info/metadata.json
open_humans_tornado_oauth2-2.1.0.dist-info/top_level.txt
