Metadata-Version: 2.0
Name: open-humans-tornado-oauth2
Version: 2.1.0
Summary: An Open Humans OAuth2 authentication provider for Tornado
Home-page: https://github.com/PersonalGenomesOrg/open-humans-tornado-oauth2
Author: Beau Gunderson
Author-email: beau@personalgenomes.org
License: UNKNOWN
Platform: UNKNOWN
Classifier: Programming Language :: Python
Classifier: Programming Language :: Python :: 3
Classifier: Development Status :: 4 - Beta
Classifier: Environment :: Other Environment
Classifier: Intended Audience :: Developers
Classifier: License :: OSI Approved :: MIT License
Classifier: Operating System :: OS Independent
Classifier: Topic :: Software Development :: Libraries :: Python Modules
